kicad_package_manager/__init__.py
kicad_package_manager/build.py
kicad_package_manager/config.py
kicad_package_manager/init.py
kicad_package_manager/init_package.py
kicad_package_manager/install.py
kicad_package_manager/kicad_project_tables.py
kicad_package_manager/kpm.py
kicad_package_manager/listt.py
kicad_package_manager/registry.py
kicad_package_manager/run.py
kicad_package_manager/search.py
kicad_package_manager/show.py
kicad_package_manager/upload.py
kicad_package_manager-0.0.23.dist-info/LICENSE
kicad_package_manager-0.0.23.dist-info/METADATA
kicad_package_manager-0.0.23.dist-info/WHEEL
kicad_package_manager-0.0.23.dist-info/entry_points.txt
kicad_package_manager-0.0.23.dist-info/top_level.txt
kicad_package_manager-0.0.23.dist-info/RECORD
