Metadata-Version: 2.1
Name: kicad-package-manager
Version: 0.0.23
Summary: A package manager for KiCad projects
Home-page: https://github.com/danroblewis/kicad-package-manager
Author: Daniel Lewis
Author-email: daniel.robert.lewis@gmail.com
License: MIT
Platform: UNKNOWN
Classifier: License :: OSI Approved :: MIT License
Classifier: Programming Language :: Python
Classifier: Programming Language :: Python :: 3
Classifier: Programming Language :: Python :: 3.6
Classifier: Programming Language :: Python :: Implementation :: CPython
Classifier: Programming Language :: Python :: Implementation :: PyPy
Requires-Python: >=3.7.0
Requires-Dist: requests
Requires-Dist: sexpdata
